{"namedChunkGroups":{"polyfill":{"name":"polyfill","assets":[{"name":"webpack-runtime-28fcf5d27da71abbc536.js","size":4522},{"name":"polyfill-f6130e90d21821a07461.js","size":82511}],"filteredAssets":0,"assetsSize":87033,"filteredAuxiliaryAssets":2,"auxiliaryAssetsSize":218902},"app":{"name":"app","assets":[{"name":"webpack-runtime-28fcf5d27da71abbc536.js","size":4522},{"name":"framework-cb779f30208c99cebed9.js","size":128898},{"name":"app-395872a9ada90ae72298.js","size":50439}],"filteredAssets":0,"assetsSize":183859,"filteredAuxiliaryAssets":3,"auxiliaryAssetsSize":547337},"component---src-pages-404-tsx":{"name":"component---src-pages-404-tsx","assets":[{"name":"styles.d50aac427f78a492ec66.css","size":1492},{"name":"commons-36d47a465e15c35c3a45.js","size":32869},{"name":"component---src-pages-404-tsx-cba1fe43e1f97ffc3855.js","size":304}],"filteredAssets":0,"assetsSize":34665,"filteredAuxiliaryAssets":2,"auxiliaryAssetsSize":87173},"component---src-pages-about-tsx":{"name":"component---src-pages-about-tsx","assets":[{"name":"styles.d50aac427f78a492ec66.css","size":1492},{"name":"commons-36d47a465e15c35c3a45.js","size":32869},{"name":"component---src-pages-about-tsx-48c0ca9fb79a351f2a2b.js","size":2349}],"filteredAssets":0,"assetsSize":36710,"filteredAuxiliaryAssets":2,"auxiliaryAssetsSize":89761},"component---src-pages-blog-tsx":{"name":"component---src-pages-blog-tsx","assets":[{"name":"styles.d50aac427f78a492ec66.css","size":1492},{"name":"commons-36d47a465e15c35c3a45.js","size":32869},{"name":"component---src-pages-blog-tsx-f545fa3276daa3c766d2.js","size":341}],"filteredAssets":0,"assetsSize":34702,"filteredAuxiliaryAssets":2,"auxiliaryAssetsSize":86932},"component---src-pages-gallery-tsx":{"name":"component---src-pages-gallery-tsx","assets":[{"name":"styles.d50aac427f78a492ec66.css","size":1492},{"name":"commons-36d47a465e15c35c3a45.js","size":32869},{"name":"component---src-pages-gallery-tsx-c8373869b0f19dae4283.js","size":343}],"filteredAssets":0,"assetsSize":34704,"filteredAuxiliaryAssets":2,"auxiliaryAssetsSize":86938},"component---src-pages-index-tsx":{"name":"component---src-pages-index-tsx","assets":[{"name":"styles.d50aac427f78a492ec66.css","size":1492},{"name":"commons-36d47a465e15c35c3a45.js","size":32869},{"name":"component---src-pages-index-tsx-61e9047162a1bad2347d.js","size":2428}],"filteredAssets":0,"assetsSize":36789,"filteredAuxiliaryAssets":2,"auxiliaryAssetsSize":89903}},"assetsByChunkName":{"polyfill":["webpack-runtime-28fcf5d27da71abbc536.js","polyfill-f6130e90d21821a07461.js"],"app":["webpack-runtime-28fcf5d27da71abbc536.js","framework-cb779f30208c99cebed9.js","app-395872a9ada90ae72298.js"],"component---src-pages-404-tsx":["styles.d50aac427f78a492ec66.css","commons-36d47a465e15c35c3a45.js","component---src-pages-404-tsx-cba1fe43e1f97ffc3855.js"],"component---src-pages-about-tsx":["styles.d50aac427f78a492ec66.css","commons-36d47a465e15c35c3a45.js","component---src-pages-about-tsx-48c0ca9fb79a351f2a2b.js"],"component---src-pages-blog-tsx":["styles.d50aac427f78a492ec66.css","commons-36d47a465e15c35c3a45.js","component---src-pages-blog-tsx-f545fa3276daa3c766d2.js"],"component---src-pages-gallery-tsx":["styles.d50aac427f78a492ec66.css","commons-36d47a465e15c35c3a45.js","component---src-pages-gallery-tsx-c8373869b0f19dae4283.js"],"component---src-pages-index-tsx":["styles.d50aac427f78a492ec66.css","commons-36d47a465e15c35c3a45.js","component---src-pages-index-tsx-61e9047162a1bad2347d.js"]},"childAssetsByChunkName":{}}